napari_correct_drift/__init__.py
napari_correct_drift/_core.py
napari_correct_drift/_sample_data.py
napari_correct_drift/_widget.py
napari_correct_drift/napari.yaml
napari_correct_drift/_tests/__init__.py
napari_correct_drift/_tests/test_core.py
napari_correct_drift/_tests/test_sample_data.py
napari_correct_drift/_tests/test_widget.py
napari_correct_drift-0.4.0.dist-info/LICENSE
napari_correct_drift-0.4.0.dist-info/METADATA
napari_correct_drift-0.4.0.dist-info/WHEEL
napari_correct_drift-0.4.0.dist-info/entry_points.txt
napari_correct_drift-0.4.0.dist-info/top_level.txt
napari_correct_drift-0.4.0.dist-info/RECORD
