Metadata-Version: 2.1
Name: napari-correct-drift
Version: 0.4.0
Summary: Drift correction 2D/3D for Napari similar to Fijis Correct 3D drift macro
Home-page: https://github.com/sommerc/napari-correct-drift
Author: Christoph Sommer
Author-email: christoph.sommer@ist.ac.at
License: BSD-3-Clause
Project-URL: Bug Tracker, https://github.com/sommerc/napari-correct-drift/issues
Project-URL: Documentation, https://github.com/sommerc/napari-correct-drift#README.md
Project-URL: Source Code, https://github.com/sommerc/napari-correct-drift
Project-URL: User Support, https://github.com/sommerc/napari-correct-drift/issues
Classifier: Development Status :: 2 - Pre-Alpha
Classifier: Framework :: napari
Classifier: Intended Audience :: Developers
Classifier: License :: OSI Approved :: BSD License
Classifier: Operating System :: OS Independent
Classifier: Programming Language :: Python
Classifier: Programming Language :: Python :: 3
Classifier: Programming Language :: Python :: 3 :: Only
Classifier: Programming Language :: Python :: 3.8
Classifier: Programming Language :: Python :: 3.9
Classifier: Programming Language :: Python :: 3.10
Classifier: Topic :: Scientific/Engineering :: Image Processing
Requires-Python: >=3.8
License-File: LICENSE
Requires-Dist: napari
Requires-Dist: numpy
Requires-Dist: qtpy
Requires-Dist: pandas
Requires-Dist: scikit-image
Requires-Dist: scipy
Requires-Dist: dask
Provides-Extra: testing
Requires-Dist: tox ; extra == 'testing'
Requires-Dist: pytest ; extra == 'testing'
Requires-Dist: pytest-cov ; extra == 'testing'
Requires-Dist: pytest-qt ; extra == 'testing'
Requires-Dist: napari ; extra == 'testing'
Requires-Dist: pyqt5 ; extra == 'testing'
